LICENSE
MANIFEST.in
README.md
setup.cfg
setup.py
drftest/__init__.py
drftest/abc_test_meta.py
drftest/auth_provider.py
drftest/base_authenticated_view_test.py
drftest/base_view_test.py
drftest/doc_generator.py
drftest/test_runner.py
drftest/token_auth_provider.py
drftest/uuid_encoder.py
drftest.egg-info/PKG-INFO
drftest.egg-info/SOURCES.txt
drftest.egg-info/dependency_links.txt
drftest.egg-info/requires.txt
drftest.egg-info/top_level.txt
drftest/templates/doc_of_app.md
drftest/templatetags/__init__.py
drftest/templatetags/doc_filters.py
drftest/tests/__init__.py
drftest/tests/doc_schema.py
drftest/tests/test_doc_generator.py
drftest/tests/test_settings.py
drftest/tests/test_views.py