Metadata-Version: 1.1
Name: drftest
Version: 1.0.2
Summary: drftest is a minimal testing library that aims to facilitate writing tests for django rest framework views. It also [optionally] generates good looking API documentations based on tests it runs.
Home-page: https://github.com/pdrum/drftest
Author: Pedram Hajesmaeeli
Author-email: pedram.esmaeeli@gmail.com
License: MIT License
Platform: UNKNOWN
Classifier: Environment :: Web Environment
Classifier: Framework :: Django
Classifier: Intended Audience :: Developers
Classifier: License :: OSI Approved :: MIT License
Classifier: Programming Language :: Python
Classifier: Topic :: Internet :: WWW/HTTP
Classifier: Topic :: Internet :: WWW/HTTP :: Dynamic Content
